openstack_governance/__init__.py
openstack_governance/_check_schema.py
openstack_governance/_wiki.py
openstack_governance/_yamlutils.py
openstack_governance/governance.py
openstack_governance/members.py
openstack_governance/projects.py
openstack_governance/projects_schema.yaml
openstack_governance/yamltools.py
openstack_governance/tests/__init__.py
openstack_governance/tests/test_governance.py
openstack_governance-0.19.0.dist-info/AUTHORS
openstack_governance-0.19.0.dist-info/METADATA
openstack_governance-0.19.0.dist-info/WHEEL
openstack_governance-0.19.0.dist-info/entry_points.txt
openstack_governance-0.19.0.dist-info/pbr.json
openstack_governance-0.19.0.dist-info/top_level.txt
openstack_governance-0.19.0.dist-info/RECORD
