Metadata-Version: 2.1
Name: openstack-governance
Version: 0.19.0
Summary: OpenStack Governance Documents
Home-page: http://www.openstack.org/
Author: OpenStack TC
Author-email: openstack-tc@lists.openstack.org
License-File: AUTHORS
Requires-Dist: pydot
Requires-Dist: PyYAML >=3.1.0
Requires-Dist: yamlordereddictloader
Requires-Dist: mwclient ==0.8.1
Requires-Dist: ruamel.yaml
Requires-Dist: jsonschema >=3.2.0
